baseEmoji/__init__.py
baseEmoji/baseEmoji.py
baseEmoji-0.1.1.dist-info/DESCRIPTION.rst
baseEmoji-0.1.1.dist-info/METADATA
baseEmoji-0.1.1.dist-info/RECORD
baseEmoji-0.1.1.dist-info/WHEEL
baseEmoji-0.1.1.dist-info/metadata.json
baseEmoji-0.1.1.dist-info/namespace_packages.txt
baseEmoji-0.1.1.dist-info/top_level.txt
