Metadata-Version: 2.0
Name: baseEmoji
Version: 0.1.1
Summary: A simple base1024 encoder that outputs emoji.
Home-page: http://github.com/tsunaminoai/baseemoji
Author: Ben Craton
Author-email: tsunaminoai@gmail.com
License: MIT
Keywords: base1024 encode emoji
Platform: UNKNOWN
Classifier: Development Status :: 4 - Beta
Classifier: Intended Audience :: Developers
Classifier: License :: OSI Approved :: MIT License
Classifier: Operating System :: OS Independent
Classifier: Programming Language :: Python :: 2.6
Classifier: Programming Language :: Python :: 2.7
Classifier: Programming Language :: Python :: 3.4
Classifier: Programming Language :: Python :: 3.6
Requires-Dist: uniseg
